MANIFEST.in
README.md
install-requirements.txt
setup.py
heptapod_api_import/VERSION
heptapod_api_import/__init__.py
heptapod_api_import/api.py
heptapod_api_import/base.py
heptapod_api_import/datetime.py
heptapod_api_import/issues.py
heptapod_api_import/labels.py
heptapod_api_import/objects.py
heptapod_api_import/user_mapping.py
heptapod_api_import.egg-info/PKG-INFO
heptapod_api_import.egg-info/SOURCES.txt
heptapod_api_import.egg-info/dependency_links.txt
heptapod_api_import.egg-info/entry_points.txt
heptapod_api_import.egg-info/requires.txt
heptapod_api_import.egg-info/top_level.txt